natpy/__init__.py
natpy/constants.py
natpy/convert.py
natpy/default_values.py
natpy/natural_unit_class.py
NatPy_andre_scaffidi-0.0.3.dist-info/LICENSE
NatPy_andre_scaffidi-0.0.3.dist-info/METADATA
NatPy_andre_scaffidi-0.0.3.dist-info/WHEEL
NatPy_andre_scaffidi-0.0.3.dist-info/top_level.txt
NatPy_andre_scaffidi-0.0.3.dist-info/RECORD
