Metadata-Version: 2.1
Name: NatPy-andre-scaffidi
Version: 0.0.3
Summary: Convert the units of particle physics quantities.
Home-page: https://github.com/AndreScaffidi/NatPy
Author: Tomas Howson and Andre Scaffidi
Author-email: tomas.howson@adelaide.edu.au, andre.scaffidi@adelaide.edu.au
License: UNKNOWN
Platform: UNKNOWN
Classifier: Programming Language :: Python :: 3
Classifier: License :: OSI Approved :: MIT License
Classifier: Operating System :: OS Independent
Requires-Python: >=3.7
